ravenrpc/__init__.py
ravenrpc/setup.py
ravenrpc-0.2.4.dist-info/METADATA
ravenrpc-0.2.4.dist-info/WHEEL
ravenrpc-0.2.4.dist-info/top_level.txt
ravenrpc-0.2.4.dist-info/RECORD
