Metadata-Version: 2.1
Name: ravenrpc
Version: 0.2.4
Summary: Ravencoin RPC client
Home-page: https://github.com/JonPizza/ravenrpc
Author: JonPizza
Author-email: jon@jon.network
License: UNKNOWN
Platform: UNKNOWN
Classifier: Programming Language :: Python :: 3
Classifier: License :: OSI Approved :: MIT License
Classifier: Operating System :: OS Independent
Requires-Python: >=3.6
